{
  "name": "pulse-嗯？这是啥-9088718",
  "source_file": "pulse-嗯？这是啥-9088718.pulse",
  "num_ops": 329,
  "header": {
    "rest_ticks": 99,
    "speed": 1,
    "param3": 8,
    "raw": "99,1,8"
  },
  "preview_sections": [
    {
      "freq_low": 0,
      "freq_high": 20,
      "freq_mode": 1,
      "duration": 67,
      "n_points": 2,
      "repeats": 34,
      "points": [
        {
          "strength": 0,
          "anchor": true
        },
        {
          "strength": 100,
          "anchor": true
        }
      ]
    },
    {
      "freq_low": 5,
      "freq_high": 20,
      "freq_mode": 1,
      "duration": 17,
      "n_points": 2,
      "repeats": 9,
      "points": [
        {
          "strength": 100,
          "anchor": true
        },
        {
          "strength": 100,
          "anchor": true
        }
      ]
    },
    {
      "freq_low": 27,
      "freq_high": 20,
      "freq_mode": 1,
      "duration": 10,
      "n_points": 2,
      "repeats": 5,
      "points": [
        {
          "strength": 100,
          "anchor": true
        },
        {
          "strength": 100,
          "anchor": true
        }
      ]
    },
    {
      "freq_low": 0,
      "freq_high": 20,
      "freq_mode": 1,
      "duration": 53,
      "n_points": 2,
      "repeats": 27,
      "points": [
        {
          "strength": 40,
          "anchor": true
        },
        {
          "strength": 100,
          "anchor": true
        }
      ]
    },
    {
      "freq_low": 0,
      "freq_high": 20,
      "freq_mode": 1,
      "duration": 57,
      "n_points": 6,
      "repeats": 10,
      "points": [
        {
          "strength": 100,
          "anchor": true
        },
        {
          "strength": 0,
          "anchor": true
        },
        {
          "strength": 100,
          "anchor": true
        },
        {
          "strength": 50,
          "anchor": false
        },
        {
          "strength": 0,
          "anchor": true
        },
        {
          "strength": 0,
          "anchor": true
        }
      ]
    },
    {
      "freq_low": 0,
      "freq_high": 20,
      "freq_mode": 1,
      "duration": 20,
      "n_points": 10,
      "repeats": 2,
      "points": [
        {
          "strength": 0,
          "anchor": true
        },
        {
          "strength": 50,
          "anchor": false
        },
        {
          "strength": 100,
          "anchor": true
        },
        {
          "strength": 0,
          "anchor": true
        },
        {
          "strength": 45,
          "anchor": true
        },
        {
          "strength": 75,
          "anchor": true
        },
        {
          "strength": 40,
          "anchor": true
        },
        {
          "strength": 100,
          "anchor": true
        },
        {
          "strength": 78,
          "anchor": false
        },
        {
          "strength": 55,
          "anchor": true
        }
      ]
    }
  ],
  "wavestrs": [
    "[\"0A0A0A0A00000000\",\"0A0A0A0A64646464\",\"0A0A0A0A00000000\",\"0A0A0A0A64646464\",\"0A0A0A0A00000000\",\"0A0A0A0A64646464\",\"0A0A0A0A00000000\",\"0A0A0A0A64646464\",\"0A0A0A0A00000000\",\"0A0A0A0A64646464\",\"0A0A0A0A00000000\",\"0A0A0A0A64646464\",\"0A0A0A0A00000000\",\"0A0A0A0A64646464\",\"0A0A0A0A00000000\",\"0A0A0A0A64646464\",\"0A0A0A0A00000000\",\"0A0A0A0A64646464\",\"0A0A0A0A00000000\",\"0A0A0A0A64646464\",\"0A0A0A0A00000000\",\"0A0A0A0A64646464\",\"0A0A0A0A00000000\",\"0A0A0A0A64646464\",\"0A0A0A0A00000000\",\"0A0A0A0A64646464\",\"0A0A0A0A00000000\",\"0A0A0A0A64646464\",\"0A0A0A0A00000000\",\"0A0A0A0A64646464\",\"0A0A0A0A00000000\",\"0A0A0A0A64646464\",\"0A0A0A0A00000000\",\"0A0A0A0A64646464\",\"0A0A0A0A00000000\",\"0A0A0A0A64646464\",\"0A0A0A0A00000000\",\"0A0A0A0A64646464\",\"0A0A0A0A00000000\",\"0A0A0A0A64646464\",\"0A0A0A0A00000000\",\"0A0A0A0A64646464\",\"0A0A0A0A00000000\",\"0A0A0A0A64646464\",\"0A0A0A0A00000000\",\"0A0A0A0A64646464\",\"0A0A0A0A00000000\",\"0A0A0A0A64646464\",\"0A0A0A0A00000000\",\"0A0A0A0A64646464\",\"0A0A0A0A00000000\",\"0A0A0A0A64646464\",\"0A0A0A0A00000000\",\"0A0A0A0A64646464\",\"0A0A0A0A00000000\",\"0A0A0A0A64646464\",\"0A0A0A0A00000000\",\"0A0A0A0A64646464\",\"0A0A0A0A00000000\",\"0A0A0A0A64646464\",\"0A0A0A0A00000000\",\"0A0A0A0A64646464\",\"0A0A0A0A00000000\",\"0A0A0A0A64646464\",\"0A0A0A0A00000000\",\"0A0A0A0A64646464\",\"0A0A0A0A00000000\",\"0A0A0A0A64646464\",\"0F0F0F0F64646464\",\"0F0F0F0F64646464\",\"0F0F0F0F64646464\",\"0F0F0F0F64646464\",\"0F0F0F0F64646464\",\"0F0F0F0F64646464\",\"0F0F0F0F64646464\",\"0F0F0F0F64646464\",\"0F0F0F0F64646464\",\"0F0F0F0F64646464\",\"0F0F0F0F64646464\",\"0F0F0F0F64646464\",\"0F0F0F0F64646464\",\"0F0F0F0F64646464\",\"0F0F0F0F64646464\",\"0F0F0F0F64646464\",\"0F0F0F0F64646464\",\"0F0F0F0F64646464\"]",
    "[\"2525252564646464\",\"2525252564646464\",\"2525252564646464\",\"2525252564646464\",\"2525252564646464\",\"2525252564646464\",\"2525252564646464\",\"2525252564646464\",\"2525252564646464\",\"2525252564646464\",\"0A0A0A0A28282828\",\"0A0A0A0A64646464\",\"0A0A0A0A28282828\",\"0A0A0A0A64646464\",\"0A0A0A0A28282828\",\"0A0A0A0A64646464\",\"0A0A0A0A28282828\",\"0A0A0A0A64646464\",\"0A0A0A0A28282828\",\"0A0A0A0A64646464\",\"0A0A0A0A28282828\",\"0A0A0A0A64646464\",\"0A0A0A0A28282828\",\"0A0A0A0A64646464\",\"0A0A0A0A28282828\",\"0A0A0A0A64646464\",\"0A0A0A0A28282828\",\"0A0A0A0A64646464\",\"0A0A0A0A28282828\",\"0A0A0A0A64646464\",\"0A0A0A0A28282828\",\"0A0A0A0A64646464\",\"0A0A0A0A28282828\",\"0A0A0A0A64646464\",\"0A0A0A0A28282828\",\"0A0A0A0A64646464\",\"0A0A0A0A28282828\",\"0A0A0A0A64646464\",\"0A0A0A0A28282828\",\"0A0A0A0A64646464\",\"0A0A0A0A28282828\",\"0A0A0A0A64646464\",\"0A0A0A0A28282828\",\"0A0A0A0A64646464\",\"0A0A0A0A28282828\",\"0A0A0A0A64646464\",\"0A0A0A0A28282828\",\"0A0A0A0A64646464\",\"0A0A0A0A28282828\",\"0A0A0A0A64646464\",\"0A0A0A0A28282828\",\"0A0A0A0A64646464\",\"0A0A0A0A28282828\",\"0A0A0A0A64646464\",\"0A0A0A0A28282828\",\"0A0A0A0A64646464\",\"0A0A0A0A28282828\",\"0A0A0A0A64646464\",\"0A0A0A0A28282828\",\"0A0A0A0A64646464\",\"0A0A0A0A28282828\",\"0A0A0A0A64646464\",\"0A0A0A0A28282828\",\"0A0A0A0A64646464\",\"0A0A0A0A64646464\",\"0A0A0A0A00000000\",\"0A0A0A0A64646464\",\"0A0A0A0A32323232\",\"0A0A0A0A00000000\",\"0A0A0A0A00000000\",\"0A0A0A0A64646464\",\"0A0A0A0A00000000\",\"0A0A0A0A64646464\",\"0A0A0A0A32323232\",\"0A0A0A0A00000000\",\"0A0A0A0A00000000\",\"0A0A0A0A64646464\",\"0A0A0A0A00000000\",\"0A0A0A0A64646464\",\"0A0A0A0A32323232\",\"0A0A0A0A00000000\",\"0A0A0A0A00000000\",\"0A0A0A0A64646464\",\"0A0A0A0A00000000\",\"0A0A0A0A64646464\",\"0A0A0A0A32323232\"]",
    "[\"0A0A0A0A00000000\",\"0A0A0A0A00000000\",\"0A0A0A0A64646464\",\"0A0A0A0A00000000\",\"0A0A0A0A64646464\",\"0A0A0A0A32323232\",\"0A0A0A0A00000000\",\"0A0A0A0A00000000\",\"0A0A0A0A64646464\",\"0A0A0A0A00000000\",\"0A0A0A0A64646464\",\"0A0A0A0A32323232\",\"0A0A0A0A00000000\",\"0A0A0A0A00000000\",\"0A0A0A0A64646464\",\"0A0A0A0A00000000\",\"0A0A0A0A64646464\",\"0A0A0A0A32323232\",\"0A0A0A0A00000000\",\"0A0A0A0A00000000\",\"0A0A0A0A64646464\",\"0A0A0A0A00000000\",\"0A0A0A0A64646464\",\"0A0A0A0A32323232\",\"0A0A0A0A00000000\",\"0A0A0A0A00000000\",\"0A0A0A0A64646464\",\"0A0A0A0A00000000\",\"0A0A0A0A64646464\",\"0A0A0A0A32323232\",\"0A0A0A0A00000000\",\"0A0A0A0A00000000\",\"0A0A0A0A64646464\",\"0A0A0A0A00000000\",\"0A0A0A0A64646464\",\"0A0A0A0A32323232\",\"0A0A0A0A00000000\",\"0A0A0A0A00000000\",\"0A0A0A0A00000000\",\"0A0A0A0A32323232\",\"0A0A0A0A64646464\",\"0A0A0A0A00000000\",\"0A0A0A0A2D2D2D2D\",\"0A0A0A0A4B4B4B4B\",\"0A0A0A0A28282828\",\"0A0A0A0A64646464\",\"0A0A0A0A4E4E4E4E\",\"0A0A0A0A37373737\",\"0A0A0A0A00000000\",\"0A0A0A0A32323232\",\"0A0A0A0A64646464\",\"0A0A0A0A00000000\",\"0A0A0A0A2D2D2D2D\",\"0A0A0A0A4B4B4B4B\",\"0A0A0A0A28282828\",\"0A0A0A0A64646464\",\"0A0A0A0A4E4E4E4E\",\"0A0A0A0A37373737\",\"0000000000000000\",\"0000000000000000\",\"0000000000000000\",\"0000000000000000\",\"0000000000000000\",\"0000000000000000\",\"0000000000000000\",\"0000000000000000\",\"0000000000000000\",\"0000000000000000\",\"0000000000000000\",\"0000000000000000\",\"0000000000000000\",\"0000000000000000\",\"0000000000000000\",\"0000000000000000\",\"0000000000000000\",\"0000000000000000\",\"0000000000000000\",\"0000000000000000\",\"0000000000000000\",\"0000000000000000\",\"0000000000000000\",\"0000000000000000\",\"0000000000000000\",\"0000000000000000\",\"0000000000000000\",\"0000000000000000\"]",
    "[\"0000000000000000\",\"0000000000000000\",\"0000000000000000\",\"0000000000000000\",\"0000000000000000\",\"0000000000000000\",\"0000000000000000\",\"0000000000000000\",\"0000000000000000\",\"0000000000000000\",\"0000000000000000\",\"0000000000000000\",\"0000000000000000\",\"0000000000000000\",\"0000000000000000\",\"0000000000000000\",\"0000000000000000\",\"0000000000000000\",\"0000000000000000\",\"0000000000000000\",\"0000000000000000\",\"0000000000000000\",\"0000000000000000\",\"0000000000000000\",\"0000000000000000\",\"0000000000000000\",\"0000000000000000\",\"0000000000000000\",\"0000000000000000\",\"0000000000000000\",\"0000000000000000\",\"0000000000000000\",\"0000000000000000\",\"0000000000000000\",\"0000000000000000\",\"0000000000000000\",\"0000000000000000\",\"0000000000000000\",\"0000000000000000\",\"0000000000000000\",\"0000000000000000\",\"0000000000000000\",\"0000000000000000\",\"0000000000000000\",\"0000000000000000\",\"0000000000000000\",\"0000000000000000\",\"0000000000000000\",\"0000000000000000\",\"0000000000000000\",\"0000000000000000\",\"0000000000000000\",\"0000000000000000\",\"0000000000000000\",\"0000000000000000\",\"0000000000000000\",\"0000000000000000\",\"0000000000000000\",\"0000000000000000\",\"0000000000000000\",\"0000000000000000\",\"0000000000000000\",\"0000000000000000\",\"0000000000000000\",\"0000000000000000\",\"0000000000000000\",\"0000000000000000\",\"0000000000000000\",\"0000000000000000\",\"0000000000000000\",\"0000000000000000\"]"
  ]
}
